tacoreader/__init__.py
tacoreader/_cache.py
tacoreader/_constants.py
tacoreader/_exceptions.py
tacoreader/_format.py
tacoreader/_html.py
tacoreader/_legacy.py
tacoreader/_logging.py
tacoreader/_path.py
tacoreader/_remote_io.py
tacoreader/_stac.py
tacoreader/_stac_cascade.py
tacoreader/_vsi.py
tacoreader/concat/__init__.py
tacoreader/concat/_columns.py
tacoreader/concat/_orchestrator.py
tacoreader/concat/_validation.py
tacoreader/concat/_view_builder.py
tacoreader/dataframe/__init__.py
tacoreader/dataframe/_stats.py
tacoreader/dataframe/base.py
tacoreader/dataframe/pandas.py
tacoreader/dataframe/polars.py
tacoreader/dataframe/pyarrow.py
tacoreader/dataset.py
tacoreader/loader.py
tacoreader/schema.py
tacoreader/storage/__init__.py
tacoreader/storage/base.py
tacoreader/storage/folder.py
tacoreader/storage/tacocat.py
tacoreader/storage/zip.py
tacoreader/v1/TortillaDataFrame.py
tacoreader/v1/__init__.py
tacoreader/v1/compile.py
tacoreader/v1/compile_utils.py
tacoreader/v1/loader_dataframe.py
tacoreader/v1/loader_metadata.py
tacoreader/v1/loader_utils.py
tacoreader/v1/sanity.py
tacoreader-2.4.13.dist-info/METADATA
tacoreader-2.4.13.dist-info/WHEEL
tacoreader-2.4.13.dist-info/licenses/LICENSE
tacoreader-2.4.13.dist-info/RECORD
