Metadata-Version: 2.4
Name: tacoreader
Version: 2.4.13
Summary: Query engine for AI-ready datasets.
License-Expression: MIT
License-File: LICENSE
Keywords: earth-observation,geospatial,machine-learning,satellite-imagery,remote-sensing,ai-ready-datasets,duckdb,stac
Author: Cesar Aybar
Author-email: cesar.aybar@uv.es
Requires-Python: >=3.10,<3.14
Classifier: Development Status :: 4 - Beta
Classifier: Intended Audience :: Science/Research
Classifier: License :: OSI Approved :: MIT License
Classifier: Operating System :: OS Independent
Classifier: Programming Language :: Python :: 3
Classifier: Programming Language :: Python :: 3.10
Classifier: Programming Language :: Python :: 3.11
Classifier: Programming Language :: Python :: 3.12
Classifier: Programming Language :: Python :: 3.13
Classifier: Topic :: Scientific/Engineering :: Artificial Intelligence
Classifier: Topic :: Scientific/Engineering :: GIS
Classifier: Typing :: Typed
Provides-Extra: all
Provides-Extra: pandas
Provides-Extra: polars
Provides-Extra: stats
Requires-Dist: duckdb (>=1.3.2)
Requires-Dist: numpy (>=1.24) ; extra == "all"
Requires-Dist: numpy (>=1.24) ; extra == "stats"
Requires-Dist: obstore (>=0.8.1)
Requires-Dist: pandas (>=2.0.0) ; extra == "all"
Requires-Dist: pandas (>=2.0.0) ; extra == "pandas"
Requires-Dist: platformdirs (>=4.5.1,<5.0.0)
Requires-Dist: polars (>=1.0.0) ; extra == "all"
Requires-Dist: polars (>=1.0.0) ; extra == "polars"
Requires-Dist: pyarrow (>=21.0.0)
Requires-Dist: pydantic (>=2.12.5)
Requires-Dist: tacozip (>=0.11.4)
Requires-Dist: tqdm (>=4.67.1)
Project-URL: Bug Tracker, https://github.com/tacofoundation/tacoreader/issues
Project-URL: Changelog, https://github.com/tacofoundation/tacoreader/releases
Project-URL: Documentation, https://tacofoundation.github.io/tacoreader/
Project-URL: Repository, https://github.com/tacofoundation/tacoreader
